popquotes/__init__.py
popquotes/pmxbot.py
popquotes/popquotes.sqlite
popquotes-1.5.dist-info/DESCRIPTION.rst
popquotes-1.5.dist-info/LICENSE.txt
popquotes-1.5.dist-info/METADATA
popquotes-1.5.dist-info/RECORD
popquotes-1.5.dist-info/WHEEL
popquotes-1.5.dist-info/entry_points.txt
popquotes-1.5.dist-info/metadata.json
popquotes-1.5.dist-info/namespace_packages.txt
popquotes-1.5.dist-info/top_level.txt
