Metadata-Version: 2.0
Name: popquotes
Version: 1.5
Summary: Popular Quotes database
Home-page: https://github.com/yougov/popquotes
Author: YouGov, Plc.
Author-email: dev@yougov.com
License: UNKNOWN
Platform: UNKNOWN
Classifier: Development Status :: 5 - Production/Stable
Classifier: Intended Audience :: Developers
Classifier: License :: OSI Approved :: MIT License
Classifier: Programming Language :: Python :: 3
Requires-Python: >=3.4
Requires-Dist: pmxbot
Provides-Extra: docs
Requires-Dist: sphinx; extra == 'docs'
Requires-Dist: jaraco.packaging (>=3.2); extra == 'docs'
Requires-Dist: rst.linker (>=1.9); extra == 'docs'
Provides-Extra: testing
Requires-Dist: pytest (>=2.8); extra == 'testing'
Requires-Dist: pytest-sugar (>=0.9.1); extra == 'testing'
Requires-Dist: collective.checkdocs; extra == 'testing'
